{
	"name": "dataflow6Pipelinelog1",
	"properties": {
		"type": "MappingDataFlow",
		"typeProperties": {
			"sources": [
				{
					"dataset": {
						"referenceName": "ds_dataflow_log_input1",
						"type": "DatasetReference"
					},
					"name": "source1"
				}
			],
			"sinks": [
				{
					"dataset": {
						"referenceName": "ds_dataflow_log_output1",
						"type": "DatasetReference"
					},
					"name": "sink1"
				}
			],
			"transformations": [
				{
					"name": "derivedColumn1"
				},
				{
					"name": "select1"
				}
			],
			"scriptLines": [
				"parameters{",
				"     ADFName as string,",
				"     pipelineName as string,",
				"     runtime as string,",
				"     filename as string",
				"}",
				"source(output(",
				"          dummyheader as string",
				"     ),",
				"     allowSchemaDrift: true,",
				"     validateSchema: false,",
				"     ignoreNoFilesFound: false) ~> source1",
				"source1 derive(ADFName = $ADFName,",
				"          Pipelinename = $pipelineName,",
				"          RunTime = $runtime) ~> derivedColumn1",
				"derivedColumn1 select(mapColumn(",
				"          ADFName,",
				"          Pipelinename,",
				"          RunTime",
				"     ),",
				"     skipDuplicateMapInputs: true,",
				"     skipDuplicateMapOutputs: true) ~> select1",
				"select1 sink(allowSchemaDrift: true,",
				"     validateSchema: false,",
				"     partitionFileNames:[($filename)],",
				"     umask: 0022,",
				"     preCommands: [],",
				"     postCommands: [],",
				"     skipDuplicateMapInputs: true,",
				"     skipDuplicateMapOutputs: true,",
				"     partitionBy('hash', 1)) ~> sink1"
			]
		}
	}
}