{
	"name": "pipeline16SchemaValidation",
	"properties": {
		"activities": [
			{
				"name": "Get MetadataEmp",
				"type": "GetMetadata",
				"dependsOn": [],
				"policy": {
					"timeout": "0.12:00:00",
					"retry": 0,
					"retryIntervalInSeconds": 30,
					"secureOutput": false,
					"secureInput": false
				},
				"userProperties": [],
				"typeProperties": {
					"dataset": {
						"referenceName": "ds_pipe_emp_input",
						"type": "DatasetReference"
					},
					"fieldList": [
						"structure"
					],
					"storeSettings": {
						"type": "AzureBlobFSReadSettings",
						"enablePartitionDiscovery": false
					},
					"formatSettings": {
						"type": "DelimitedTextReadSettings"
					}
				}
			},
			{
				"name": "Get MetadataEmpref",
				"type": "GetMetadata",
				"dependsOn": [],
				"policy": {
					"timeout": "0.12:00:00",
					"retry": 0,
					"retryIntervalInSeconds": 30,
					"secureOutput": false,
					"secureInput": false
				},
				"userProperties": [],
				"typeProperties": {
					"dataset": {
						"referenceName": "ds_pipe_empref_input",
						"type": "DatasetReference"
					},
					"fieldList": [
						"structure"
					],
					"storeSettings": {
						"type": "AzureBlobFSReadSettings",
						"enablePartitionDiscovery": false
					},
					"formatSettings": {
						"type": "DelimitedTextReadSettings"
					}
				}
			},
			{
				"name": "If Condition1",
				"type": "IfCondition",
				"dependsOn": [
					{
						"activity": "Get MetadataEmp",
						"dependencyConditions": [
							"Succeeded"
						]
					},
					{
						"activity": "Get MetadataEmpref",
						"dependencyConditions": [
							"Succeeded"
						]
					}
				],
				"userProperties": [],
				"typeProperties": {
					"expression": {
						"value": "@equals(activity('Get MetadataEmp').output.structure,activity('Get MetadataEmpref').output.structure)",
						"type": "Expression"
					},
					"ifFalseActivities": [
						{
							"name": "Set variable2",
							"type": "SetVariable",
							"dependsOn": [],
							"userProperties": [],
							"typeProperties": {
								"variableName": "MatchStatus",
								"value": "'No'"
							}
						}
					],
					"ifTrueActivities": [
						{
							"name": "Set variable1",
							"type": "SetVariable",
							"dependsOn": [],
							"userProperties": [],
							"typeProperties": {
								"variableName": "MatchStatus",
								"value": "'Yes'"
							}
						}
					]
				}
			}
		],
		"variables": {
			"MatchStatus": {
				"type": "String"
			}
		},
		"annotations": []
	}
}